m3ter/__init__.py
m3ter/_base_client.py
m3ter/_client.py
m3ter/_compat.py
m3ter/_constants.py
m3ter/_exceptions.py
m3ter/_files.py
m3ter/_models.py
m3ter/_qs.py
m3ter/_resource.py
m3ter/_response.py
m3ter/_streaming.py
m3ter/_types.py
m3ter/_version.py
m3ter/pagination.py
m3ter/py.typed
m3ter/_utils/__init__.py
m3ter/_utils/_compat.py
m3ter/_utils/_datetime_parse.py
m3ter/_utils/_logs.py
m3ter/_utils/_proxy.py
m3ter/_utils/_reflection.py
m3ter/_utils/_resources_proxy.py
m3ter/_utils/_streams.py
m3ter/_utils/_sync.py
m3ter/_utils/_transform.py
m3ter/_utils/_typing.py
m3ter/_utils/_utils.py
m3ter/lib/.keep
m3ter/resources/__init__.py
m3ter/resources/account_plans.py
m3ter/resources/accounts.py
m3ter/resources/aggregations.py
m3ter/resources/authentication.py
m3ter/resources/bill_config.py
m3ter/resources/bill_jobs.py
m3ter/resources/charges.py
m3ter/resources/commitments.py
m3ter/resources/compound_aggregations.py
m3ter/resources/contracts.py
m3ter/resources/counter_adjustments.py
m3ter/resources/counter_pricings.py
m3ter/resources/counters.py
m3ter/resources/credit_reasons.py
m3ter/resources/currencies.py
m3ter/resources/custom_fields.py
m3ter/resources/debit_reasons.py
m3ter/resources/events.py
m3ter/resources/external_mappings.py
m3ter/resources/integration_configurations.py
m3ter/resources/meters.py
m3ter/resources/notification_configurations.py
m3ter/resources/organization_config.py
m3ter/resources/permission_policies.py
m3ter/resources/plan_group_links.py
m3ter/resources/plan_groups.py
m3ter/resources/plan_templates.py
m3ter/resources/plans.py
m3ter/resources/pricings.py
m3ter/resources/products.py
m3ter/resources/resource_groups.py
m3ter/resources/scheduled_event_configurations.py
m3ter/resources/transaction_types.py
m3ter/resources/webhooks.py
m3ter/resources/balances/__init__.py
m3ter/resources/balances/balances.py
m3ter/resources/balances/charge_schedules.py
m3ter/resources/balances/transaction_schedules.py
m3ter/resources/balances/transactions.py
m3ter-0.8.0.dist-info/METADATA
m3ter-0.8.0.dist-info/WHEEL
m3ter-0.8.0.dist-info/licenses/LICENSE
m3ter-0.8.0.dist-info/RECORD
